LICENSE
MANIFEST.in
README
pyproject.toml
setup.py
cnn2snn/__init__.py
cnn2snn/akida_versions.py
cnn2snn/cli.py
cnn2snn/cnn2snn_objects.py
cnn2snn/compatibility_checks.py
cnn2snn/converter.py
cnn2snn/min_value_constraint.py
cnn2snn/model_generator.py
cnn2snn/quantization.py
cnn2snn/quantization_layers.py
cnn2snn/quantization_ops.py
cnn2snn/utils.py
cnn2snn/version.py
cnn2snn/weights_ops.py
cnn2snn.egg-info/PKG-INFO
cnn2snn.egg-info/SOURCES.txt
cnn2snn.egg-info/dependency_links.txt
cnn2snn.egg-info/entry_points.txt
cnn2snn.egg-info/requires.txt
cnn2snn.egg-info/top_level.txt
cnn2snn/calibration/__init__.py
cnn2snn/calibration/adaround.py
cnn2snn/calibration/bias_correction.py
cnn2snn/calibration/calibration.py
cnn2snn/quantizeml/__init__.py
cnn2snn/quantizeml/activations.py
cnn2snn/quantizeml/add.py
cnn2snn/quantizeml/block_converter.py
cnn2snn/quantizeml/block_converters_generator.py
cnn2snn/quantizeml/blocks.py
cnn2snn/quantizeml/btc_common.py
cnn2snn/quantizeml/buffer_temp_conv.py
cnn2snn/quantizeml/concatenate.py
cnn2snn/quantizeml/conv2d_transpose.py
cnn2snn/quantizeml/conv_common.py
cnn2snn/quantizeml/convolution.py
cnn2snn/quantizeml/dense.py
cnn2snn/quantizeml/depthwise_buffer_temp_conv.py
cnn2snn/quantizeml/depthwise_conv2d.py
cnn2snn/quantizeml/depthwise_conv2d_transpose.py
cnn2snn/quantizeml/dequantizer.py
cnn2snn/quantizeml/extract_token.py
cnn2snn/quantizeml/input_conv.py
cnn2snn/quantizeml/input_data.py
cnn2snn/quantizeml/input_quantizer.py
cnn2snn/quantizeml/layer_utils.py
cnn2snn/quantizeml/model_generator.py
cnn2snn/quantizeml/outputs.py
cnn2snn/quantizeml/padding.py
cnn2snn/quantizeml/pooling.py
cnn2snn/quantizeml/separable_convolution.py
cnn2snn/quantizeml/stateful_recurrent.py
cnn2snn/quantizeml/weights.py
cnn2snn/quantizeml/onnx_conversion/__init__.py
cnn2snn/quantizeml/onnx_conversion/activation.py
cnn2snn/quantizeml/onnx_conversion/add.py
cnn2snn/quantizeml/onnx_conversion/base_converter.py
cnn2snn/quantizeml/onnx_conversion/buffer_temp_conv.py
cnn2snn/quantizeml/onnx_conversion/concatenate.py
cnn2snn/quantizeml/onnx_conversion/conv2d.py
cnn2snn/quantizeml/onnx_conversion/conv2d_transpose.py
