Metadata-Version: 2.4
Name: cnn2snn
Version: 2.18.2
Summary: Keras to Akida CNN Converter
Home-page: https://doc.brainchipinc.com
Author: Johan Mejia
Author-email: jmejia@brainchip.com
License: Apache 2.0
Requires-Python: >=3.10
License-File: LICENSE
Requires-Dist: tf_keras~=2.19.0
Requires-Dist: tensorflow~=2.19.0
Requires-Dist: akida==2.18.2
Requires-Dist: quantizeml~=1.1.0
Dynamic: author
Dynamic: author-email
Dynamic: description
Dynamic: description-content-type
Dynamic: home-page
Dynamic: license
Dynamic: license-file
Dynamic: requires-dist
Dynamic: requires-python
Dynamic: summary
